voting/__init__.py
voting/admin.py
voting/apps.py
voting/managers.py
voting/models.py
voting/urls.py
voting/views.py
voting/migrations/0001_initial.py
voting/migrations/0002_alter_vote_object_id.py
voting/migrations/__init__.py
voting/templatetags/__init__.py
voting/templatetags/voting_tags.py
voting/utils/__init__.py
voting/utils/user_model.py
django_voting-1.1.0.dist-info/LICENSE.rst
django_voting-1.1.0.dist-info/METADATA
django_voting-1.1.0.dist-info/WHEEL
django_voting-1.1.0.dist-info/top_level.txt
django_voting-1.1.0.dist-info/RECORD
