Metadata-Version: 2.1
Name: django-voting
Version: 1.1.0
Summary: Generic voting application for Django
Home-page: https://github.com/pjdelport/django-voting
Author: Jonathan Buchanan
Author-email: jonathan.buchanan@gmail.com
Maintainer: Jannis Leidel
Maintainer-email: jannis@leidel.info
Classifier: Development Status :: 4 - Beta
Classifier: Environment :: Web Environment
Classifier: Framework :: Django
Classifier: Framework :: Django :: 3.2
Classifier: Framework :: Django :: 4.0
Classifier: Framework :: Django :: 4.1
Classifier: Intended Audience :: Developers
Classifier: License :: OSI Approved :: BSD License
Classifier: Operating System :: OS Independent
Classifier: Programming Language :: Python
Classifier: Programming Language :: Python :: 3
Classifier: Programming Language :: Python :: 3 :: Only
Classifier: Programming Language :: Python :: 3.7
Classifier: Programming Language :: Python :: 3.8
Classifier: Programming Language :: Python :: 3.9
Classifier: Programming Language :: Python :: 3.10
Classifier: Programming Language :: Python :: 3.11
Classifier: Topic :: Utilities
Requires-Python: >=3.7
License-File: LICENSE.rst
Requires-Dist: Django (>=3.2)
